janusx-1.0.10.dist-info/METADATA
janusx-1.0.10.dist-info/WHEEL
janusx-1.0.10.dist-info/entry_points.txt
janusx-1.0.10.dist-info/licenses/LICENSE
janusx/__init__.py
janusx/bioplotkit/LDBlock.py
janusx/bioplotkit/__init__.py
janusx/bioplotkit/gffplot.py
janusx/bioplotkit/gsplot.py
janusx/bioplotkit/manhanden.py
janusx/bioplotkit/manhandenraw.py
janusx/bioplotkit/pcshow.py
janusx/bioplotkit/sci_set.py
janusx/gfreader/__init__.py
janusx/gfreader/base.py
janusx/gfreader/gfreader.py
janusx/gfreader/gmerge.py
janusx/gfreader/ref_adjust.py
janusx/janusx.cp313-win_amd64.pyd
janusx/pyBLUP/QK2.py
janusx/pyBLUP/__init__.py
janusx/pyBLUP/assoc.py
janusx/pyBLUP/bayes.py
janusx/pyBLUP/gwas.py
janusx/pyBLUP/kfold.py
janusx/pyBLUP/mlm.py
janusx/script/JanusX.py
janusx/script/_common/log.py
janusx/script/_common/readanno.py
janusx/script/gmerge.py
janusx/script/grm.py
janusx/script/gs.py
janusx/script/gwas.py
janusx/script/pca.py
janusx/script/postGWAS.py
janusx/script/sim.py
janusx-1.0.10.dist-info/RECORD
