Metadata-Version: 2.4
Name: janusx
Version: 1.0.10
Requires-Dist: numpy
Requires-Dist: pandas<3.0
Requires-Dist: scipy
Requires-Dist: matplotlib
Requires-Dist: psutil
Requires-Dist: tqdm
Requires-Dist: joblib==1.5.2
License-File: LICENSE
Summary: A Suite of Genotyping Tools for Genome-Wide Association Study and Genomic Selection
Keywords: GWAS,GS,REML,PCA
Author-email: Jingxian FU <827888724@qq.com>
Requires-Python: >=3.10, <3.14
